{
    "type": "FeatureCollection",
    "features": [
	{
	    "type": "Feature",
	    "bbox": [-180.0, -90.0, 180.0, 90.0],
	    "geometry": {
		"type": "Point",
		"coordinates": [
		    23.423668000000003,
		    37.750149
		]
	    },
	    "properties": {
		"marker-symbol": "circle",
		"name": "Aegina",
		"urn": "urn:cite:etc"
	    }
	}



    ]
}
